<DOMSymbolItem xmlns:xsi="http://www.w3.org/2001/XMLSchema-instance" xmlns="http://ns.adobe.com/xfl/2008/" name="元件/shape_004" itemID="64d21051-00000490" symbolType="graphic" lastModified="1691488337">
  <timeline>
    <DOMTimeline name="shape_004">
      <layers>
        <DOMLayer name="图层 1" color="#4F80FF" current="true" isSelected="true">
          <frames>
            <DOMFrame index="0" duration="2" keyMode="9728">
              <elements>
                <DOMBitmapInstance libraryItemName="图片/picture_090">
                  <matrix>
                    <Matrix tx="16.4" ty="-71.35"/>
                  </matrix>
                </DOMBitmapInstance>
              </elements>
            </DOMFrame>
            <DOMFrame index="2" duration="2" keyMode="9728">
              <elements>
                <DOMBitmapInstance libraryItemName="图片/picture_091">
                  <matrix>
                    <Matrix tx="16.4" ty="-140.7"/>
                  </matrix>
                </DOMBitmapInstance>
              </elements>
            </DOMFrame>
            <DOMFrame index="4" duration="2" keyMode="9728">
              <elements>
                <DOMBitmapInstance libraryItemName="图片/picture_092">
                  <matrix>
                    <Matrix tx="16.4" ty="-210"/>
                  </matrix>
                </DOMBitmapInstance>
              </elements>
            </DOMFrame>
            <DOMFrame index="6" duration="2" keyMode="9728">
              <elements>
                <DOMBitmapInstance libraryItemName="图片/picture_094">
                  <matrix>
                    <Matrix tx="16.4" ty="-279.35"/>
                  </matrix>
                </DOMBitmapInstance>
              </elements>
            </DOMFrame>
            <DOMFrame index="8" duration="2" keyMode="9728">
              <elements>
                <DOMBitmapInstance libraryItemName="图片/picture_095">
                  <matrix>
                    <Matrix tx="16.4" ty="-348.65"/>
                  </matrix>
                </DOMBitmapInstance>
              </elements>
            </DOMFrame>
            <DOMFrame index="10" duration="2" keyMode="9728">
              <elements>
                <DOMBitmapInstance libraryItemName="图片/picture_096">
                  <matrix>
                    <Matrix tx="16.4" ty="-418"/>
                  </matrix>
                </DOMBitmapInstance>
              </elements>
            </DOMFrame>
            <DOMFrame index="12" duration="2" keyMode="9728">
              <elements>
                <DOMBitmapInstance libraryItemName="图片/picture_097">
                  <matrix>
                    <Matrix tx="16.4" ty="-487.35"/>
                  </matrix>
                </DOMBitmapInstance>
              </elements>
            </DOMFrame>
            <DOMFrame index="14" duration="2" keyMode="9728">
              <elements>
                <DOMBitmapInstance libraryItemName="图片/picture_098">
                  <matrix>
                    <Matrix tx="16.4" ty="-556.65"/>
                  </matrix>
                </DOMBitmapInstance>
              </elements>
            </DOMFrame>
          </frames>
        </DOMLayer>
      </layers>
    </DOMTimeline>
  </timeline>
</DOMSymbolItem>