<DOMSymbolItem xmlns:xsi="http://www.w3.org/2001/XMLSchema-instance" xmlns="http://ns.adobe.com/xfl/2008/" name="元件/shape_0015" itemID="64785e0b-00000c13" sourceFlashFilepath="../../../../../../../../lenovo/Desktop/BVN/ichigo_halfmask.fla" sourceLibraryItemHRef="元件 21" sourceLastModified="1492443998" symbolType="graphic" lastModified="1685609995" sourceItemID="00000000-ffffffff">
  <timeline>
    <DOMTimeline name="shape_0015" currentFrame="52">
      <layers>
        <DOMLayer name="图层 1" color="#4FFF4F" current="true" isSelected="true">
          <frames>
            <DOMFrame index="0" duration="2" keyMode="9728">
              <elements>
                <DOMBitmapInstance libraryItemName="图片/picture_0042"/>
              </elements>
            </DOMFrame>
            <DOMFrame index="2" duration="2" keyMode="9728">
              <elements>
                <DOMBitmapInstance libraryItemName="图片/picture_0752"/>
              </elements>
            </DOMFrame>
            <DOMFrame index="4" duration="2" keyMode="9728">
              <elements>
                <DOMBitmapInstance libraryItemName="图片/picture_0753"/>
              </elements>
            </DOMFrame>
            <DOMFrame index="6" duration="2" keyMode="9728">
              <elements>
                <DOMBitmapInstance libraryItemName="图片/picture_0754"/>
              </elements>
            </DOMFrame>
            <DOMFrame index="8" duration="2" keyMode="9728">
              <elements>
                <DOMBitmapInstance libraryItemName="图片/picture_0755"/>
              </elements>
            </DOMFrame>
            <DOMFrame index="10" duration="2" keyMode="9728">
              <elements>
                <DOMBitmapInstance libraryItemName="图片/picture_0756"/>
              </elements>
            </DOMFrame>
            <DOMFrame index="12" duration="2" keyMode="9728">
              <elements>
                <DOMBitmapInstance libraryItemName="图片/picture_0757"/>
              </elements>
            </DOMFrame>
            <DOMFrame index="14" duration="2" keyMode="9728">
              <elements>
                <DOMBitmapInstance libraryItemName="图片/picture_0758"/>
              </elements>
            </DOMFrame>
            <DOMFrame index="16" duration="2" keyMode="9728">
              <elements>
                <DOMBitmapInstance libraryItemName="图片/picture_0759"/>
              </elements>
            </DOMFrame>
            <DOMFrame index="18" duration="2" keyMode="9728">
              <elements>
                <DOMBitmapInstance libraryItemName="图片/picture_0760"/>
              </elements>
            </DOMFrame>
            <DOMFrame index="20" duration="2" keyMode="9728">
              <elements>
                <DOMBitmapInstance libraryItemName="图片/picture_0761"/>
              </elements>
            </DOMFrame>
            <DOMFrame index="22" duration="2" keyMode="9728">
              <elements>
                <DOMBitmapInstance libraryItemName="图片/picture_0762"/>
              </elements>
            </DOMFrame>
            <DOMFrame index="24" duration="2" keyMode="9728">
              <elements>
                <DOMBitmapInstance libraryItemName="图片/picture_0763"/>
              </elements>
            </DOMFrame>
            <DOMFrame index="26" duration="2" keyMode="9728">
              <elements>
                <DOMBitmapInstance libraryItemName="图片/picture_0764"/>
              </elements>
            </DOMFrame>
            <DOMFrame index="28" duration="2" keyMode="9728">
              <elements>
                <DOMBitmapInstance libraryItemName="图片/picture_0765"/>
              </elements>
            </DOMFrame>
            <DOMFrame index="30" duration="2" keyMode="9728">
              <elements>
                <DOMBitmapInstance libraryItemName="图片/picture_0766"/>
              </elements>
            </DOMFrame>
            <DOMFrame index="32" duration="2" keyMode="9728">
              <elements>
                <DOMBitmapInstance libraryItemName="图片/picture_0767"/>
              </elements>
            </DOMFrame>
            <DOMFrame index="34" duration="2" keyMode="9728">
              <elements>
                <DOMBitmapInstance libraryItemName="图片/picture_0769"/>
              </elements>
            </DOMFrame>
            <DOMFrame index="36" duration="2" keyMode="9728">
              <elements>
                <DOMBitmapInstance libraryItemName="图片/picture_0770"/>
              </elements>
            </DOMFrame>
            <DOMFrame index="38" duration="2" keyMode="9728">
              <elements>
                <DOMBitmapInstance libraryItemName="图片/picture_0771"/>
              </elements>
            </DOMFrame>
            <DOMFrame index="40" duration="2" keyMode="9728">
              <elements>
                <DOMBitmapInstance libraryItemName="图片/picture_0772"/>
              </elements>
            </DOMFrame>
            <DOMFrame index="42" duration="2" keyMode="9728">
              <elements>
                <DOMBitmapInstance libraryItemName="图片/picture_0773"/>
              </elements>
            </DOMFrame>
            <DOMFrame index="44" keyMode="9728">
              <elements>
                <DOMBitmapInstance libraryItemName="图片/picture_0774"/>
              </elements>
            </DOMFrame>
            <DOMFrame index="45" keyMode="9728">
              <elements>
                <DOMBitmapInstance libraryItemName="图片/picture_0775"/>
              </elements>
            </DOMFrame>
            <DOMFrame index="46" keyMode="9728">
              <elements>
                <DOMBitmapInstance libraryItemName="图片/picture_0776"/>
              </elements>
            </DOMFrame>
            <DOMFrame index="47" keyMode="9728">
              <elements>
                <DOMBitmapInstance libraryItemName="图片/picture_0777"/>
              </elements>
            </DOMFrame>
            <DOMFrame index="48" keyMode="9728">
              <elements>
                <DOMBitmapInstance libraryItemName="图片/picture_0778"/>
              </elements>
            </DOMFrame>
            <DOMFrame index="49" keyMode="9728">
              <elements>
                <DOMBitmapInstance libraryItemName="图片/picture_0779"/>
              </elements>
            </DOMFrame>
            <DOMFrame index="50" keyMode="9728">
              <elements>
                <DOMBitmapInstance libraryItemName="图片/picture_0780"/>
              </elements>
            </DOMFrame>
            <DOMFrame index="51" keyMode="9728">
              <elements>
                <DOMBitmapInstance libraryItemName="图片/picture_0781"/>
              </elements>
            </DOMFrame>
            <DOMFrame index="52" name="stop" labelType="name" keyMode="9728">
              <elements/>
            </DOMFrame>
          </frames>
        </DOMLayer>
      </layers>
    </DOMTimeline>
  </timeline>
</DOMSymbolItem>